{
	"schemaVersion": 1,
	"id": "crawl",
	"name": "Crawl",
	"description": "Allows you to crawl",
	"version": "${version}",
	"authors": [
		"fewizz",
		"McSkinnerOG",
		"Chocohead"
	],
	"icon": "assets/crawl/icon.png",
	"environment": "*",
	"entrypoints": { 
		"main": [
			"ru.fewizz.crawl.Crawl"
		]
	},
	"contact": {
		"homepage": "https://www.curseforge.com/minecraft/mc-mods/crawl",
		"sources": "https://github.com/fewizz/Crawl",
		"issues": "https://github.com/fewizz/Crawl/issues"
	},
	"custom": {
		"mm:early_risers": [
			"ru.fewizz.crawl.EntityPoseHack"
		]
	},
	"depends": {
		"fabricloader": ">=0.7.4",
		"fabric-key-binding-api-v1": "*",
		"fabric-networking-api-v1": "*",
		"fabric-lifecycle-events-v1": "*",
		"mm": ">=2.3",
		"minecraft": "1.17"
	},
	"mixins": [
		"mixins.crawl.json"
	]
}
